setup.py
nut/__init__.py
nut/relay.py
nut/replay.py
nut.egg-info/PKG-INFO
nut.egg-info/SOURCES.txt
nut.egg-info/dependency_links.txt
nut.egg-info/entry_points.txt
nut.egg-info/top_level.txt